heygpt/__init__.py
heygpt/api.py
heygpt/cli.py
heygpt/constant.py
heygpt/core.py
heygpt/prompts.py
heygpt/serve.py
heygpt/serve_prompts.py
heygpt/utils.py
heygptcli-0.3.7.dist-info/METADATA
heygptcli-0.3.7.dist-info/WHEEL
heygptcli-0.3.7.dist-info/entry_points.txt
heygptcli-0.3.7.dist-info/RECORD
