Metadata-Version: 2.3
Name: heygptcli
Version: 0.3.7
Summary: 
Author: Rishang
Author-email: rishang@localhost.com
Requires-Python: >=3.10,<4.0
Classifier: Programming Language :: Python :: 3
Classifier: Programming Language :: Python :: 3.10
Classifier: Programming Language :: Python :: 3.11
Classifier: Programming Language :: Python :: 3.12
Classifier: Programming Language :: Python :: 3.13
Requires-Dist: fastapi
Requires-Dist: google-generativeai
Requires-Dist: litellm (>=1.74.3,<2.0.0)
Requires-Dist: openai
Requires-Dist: prompt-toolkit (>=3.0.39,<4.0.0)
Requires-Dist: pyperclip (>=1.9.0,<2.0.0)
Requires-Dist: python-dotenv (>=1.0.0,<2.0.0)
Requires-Dist: pyyaml (>=6.0.1,<7.0.0)
Requires-Dist: requests
Requires-Dist: rich
Requires-Dist: streamlit
Requires-Dist: typer
Requires-Dist: uvicorn
